ordeq_viz_cli/__init__.py
ordeq_viz_cli/__main__.py
ordeq_viz_cli/_version.py
ordeq_viz_cli/py.typed
ordeq_viz_cli-1.1.0.dist-info/licenses/LICENSE
ordeq_viz_cli-1.1.0.dist-info/METADATA
ordeq_viz_cli-1.1.0.dist-info/WHEEL
ordeq_viz_cli-1.1.0.dist-info/entry_points.txt
ordeq_viz_cli-1.1.0.dist-info/top_level.txt
ordeq_viz_cli-1.1.0.dist-info/RECORD
