Metadata-Version: 2.4
Name: ordeq_viz_cli
Version: 1.1.0
Summary: Command line interface for Ordeq visualization
Author: Niels Neerhoff, Simon Brugman
Maintainer: Niels Neerhoff, Simon Brugman
License-Expression: MIT
Requires-Python: >=3.10
License-File: LICENSE
Requires-Dist: ordeq-viz>=1.2.0
Dynamic: license-file
